Metadata-Version: 1.0
Name: pytezerio
Version: 1.0
Summary: Pacote contendo modulo para manipulação de arquivos e diretorios
Home-page: UNKNOWN
Author: Manoel Neco Jr
Author-email: necoengenheiro@gmail.com
License: UNKNOWN
Platform: UNKNOWN
